gnf/__init__.py
gnf/__main__.py
gnf/actor_base.py
gnf/algo_utils.py
gnf/api_types.py
gnf/api_utils.py
gnf/config.py
gnf/data_classes/__init__.py
gnf/data_classes/base_g_node.py
gnf/data_classes/gps_point.py
gnf/data_classes/mixin.py
gnf/demo_methods.py
gnf/dev_utils/__init__.py
gnf/dev_utils/algo_setup.py
gnf/dev_utils/dev_discovery.py
gnf/dev_utils/dev_homeowner.py
gnf/dev_utils/dev_validator.py
gnf/dev_utils/make_plants.py
gnf/django_related/__init__.py
gnf/django_related/admin.py
gnf/django_related/apps.py
gnf/django_related/db_settings.py
gnf/django_related/migrations/0001_initial.py
gnf/django_related/migrations/__init__.py
gnf/django_related/models.py
gnf/django_related/secret-key-gen.py
gnf/django_related/settings.py
gnf/django_related/tests.py
gnf/django_related/urls.py
gnf/django_related/views.py
gnf/django_related/wsgi.py
gnf/enums/__init__.py
gnf/enums/core_g_node_role.py
gnf/enums/g_node_role.py
gnf/enums/g_node_status.py
gnf/enums/message_category.py
gnf/enums/message_category_symbol.py
gnf/enums/registry_g_node_role.py
gnf/enums/universe_type.py
gnf/errors.py
gnf/gnf_db.py
gnf/gnf_rabbit_actor.py
gnf/load_dev_data.py
gnf/manage.py
gnf/message.py
gnf/property_format.py
gnf/py.typed
gnf/python_ta_daemon.json
gnf/python_ta_daemon.py
gnf/rest_api.py
gnf/schemata/__init__.py
gnf/schemata/basegnode_ctn_create.py
gnf/schemata/basegnode_gt.py
gnf/schemata/basegnode_marketmaker_create.py
gnf/schemata/basegnode_other_create.py
gnf/schemata/basegnode_terminalasset_create.py
gnf/schemata/basegnodes_broadcast.py
gnf/schemata/basegnodes_get.py
gnf/schemata/debug_tc_reinitialize_time.py
gnf/schemata/discoverycert_algo_create.py
gnf/schemata/discoverycert_algo_transfer.py
gnf/schemata/heartbeat_a.py
gnf/schemata/initial_tadeed_algo_create.py
gnf/schemata/initial_tadeed_algo_optin.py
gnf/schemata/initial_tadeed_algo_transfer.py
gnf/schemata/message_utils.py
gnf/schemata/new_tadeed_algo_optin.py
gnf/schemata/new_tadeed_send.py
gnf/schemata/old_tadeed_algo_return.py
g_node_factory-0.0.2.dist-info/entry_points.txt
g_node_factory-0.0.2.dist-info/LICENSE
g_node_factory-0.0.2.dist-info/WHEEL
g_node_factory-0.0.2.dist-info/METADATA
g_node_factory-0.0.2.dist-info/RECORD
