Metadata-Version: 2.1
Name: g-node-factory
Version: 0.0.2
Summary: G Node Factory
Home-page: https://github.com/thegridelectric/g-node-factory
License: MIT
Author: Jessica Millar
Author-email: jmillar@gridworks-consulting.com
Requires-Python: >=3.10,<4.0
Classifier: Development Status :: 2 - Pre-Alpha
Classifier: License :: OSI Approved :: MIT License
Classifier: Programming Language :: Python :: 3
Classifier: Programming Language :: Python :: 3.10
Classifier: Programming Language :: Python :: 3.11
Requires-Dist: click (>=8.0.1)
Requires-Dist: django (>=4.1.2,<5.0.0)
Requires-Dist: fastapi (>=0.85.1,<0.86.0)
Requires-Dist: fastapi-utils (>=0.2.1,<0.3.0)
Requires-Dist: pendulum (>=2.1.2,<3.0.0)
Requires-Dist: pika (>=1.3.1,<2.0.0)
Requires-Dist: psycopg2-binary (>=2.9.5,<3.0.0)
Requires-Dist: py-algorand-sdk (>=1.19.0,<2.0.0)
Requires-Dist: pydantic (>=1.10.2,<2.0.0)
Requires-Dist: pyteal (>=0.19.0,<0.20.0)
Requires-Dist: python-dotenv (>=0.21.0,<0.22.0)
Requires-Dist: pytz (>=2022.5,<2023.0)
Requires-Dist: requests (>=2.28.1,<3.0.0)
Requires-Dist: requests-async (>=0.6.2,<0.7.0)
Requires-Dist: rich (>=12.6.0,<13.0.0)
Requires-Dist: uvicorn[standard] (>=0.19.0,<0.20.0)
Project-URL: Changelog, https://github.com/thegridelectric/g-node-factory/releases
Project-URL: Documentation, https://g-node-factory.readthedocs.io
Project-URL: Repository, https://github.com/thegridelectric/g-node-factory
